lesaviezvous/__init__.py
lesaviezvous/lesaviezvous.py
lesaviezvous-0.2.6.dist-info/LICENSE
lesaviezvous-0.2.6.dist-info/METADATA
lesaviezvous-0.2.6.dist-info/WHEEL
lesaviezvous-0.2.6.dist-info/top_level.txt
lesaviezvous-0.2.6.dist-info/RECORD
