Metadata-Version: 2.1
Name: lesaviezvous
Version: 0.2.6
Summary: Un package Python pour obtenir des informations intéressantes du monde.
Home-page: https://github.com/codingtuto/lesaviezvouspkg/
Author: Coding Team
Author-email: codingteam@telegmail.com
License: MIT
Classifier: Programming Language :: Python :: 3
Classifier: Topic :: Utilities
Requires-Python: >=3.7
License-File: LICENSE
